wareroom/__init__.py
wareroom/_version.py
wareroom/storage/__init__.py
wareroom/storage/bucket.py
wareroom/storage/client.py
wareroom/storage/credential.py
wareroom-0.0.9.dist-info/LICENSE
wareroom-0.0.9.dist-info/METADATA
wareroom-0.0.9.dist-info/WHEEL
wareroom-0.0.9.dist-info/top_level.txt
wareroom-0.0.9.dist-info/zip-safe
wareroom-0.0.9.dist-info/RECORD
